albumpl/__init__.py
albumpl/cmap/__init__.py
albumpl/cmap/cmap.py
albumpl/palette/__init__.py
albumpl/palette/palette.py
albumpl-0.3.7.dist-info/METADATA
albumpl-0.3.7.dist-info/WHEEL
albumpl-0.3.7.dist-info/top_level.txt
albumpl-0.3.7.dist-info/RECORD
