Metadata-Version: 2.4
Name: albumpl
Version: 0.3.7
Summary: Matplotlib color palettes based on album covers.
Home-page: https://github.com/avapolzin/albumpl
Author: Ava Polzin
Author-email: apolzin@uchicago.edu
License: MIT
Classifier: Development Status :: 4 - Beta
Classifier: License :: OSI Approved :: MIT License
Classifier: Operating System :: OS Independent
Classifier: Programming Language :: Python
Requires-Python: >=3
Requires-Dist: matplotlib
Dynamic: author
Dynamic: author-email
Dynamic: classifier
Dynamic: description
Dynamic: description-content-type
Dynamic: home-page
Dynamic: license
Dynamic: requires-dist
Dynamic: requires-python
Dynamic: summary
